OneDrive/Documents/VivadoCodes/count_1s/count_1s.srcs/sources_1/new/flipflopdata.v
`timescale 1ns / 1ps
//////////////////////////////////////////////////////////////////////////////////
// Company: 
// Engineer: 
// 
// Create Date: 10.05.2021 16:43:39
// Design Name: 
// Module Name: flipflopdata
// Project Name: 
// Target Devices: 
// Tool Versions: 
// Description: 
// 
// Dependencies: 
// 
// Revision:
// Revision 0.01 - File Created
// Additional Comments:
// 
//////////////////////////////////////////////////////////////////////////////////
//This flipflop has been used such that it can never get resetted

module flipflopdata(
output reg out,input in,input reset_b,input clk);
 always @(posedge clk,negedge reset_b)
   if(reset_b == 0)
     out <=  1'b0;
   else 
     out <= in;
endmodule

OneDrive/Documents/VivadoCodes/count_1s/count_1s.srcs/sources_1/new/Counter.v
`timescale 1ns / 1ps
//////////////////////////////////////////////////////////////////////////////////
// Company: 
// Engineer: 
// 
// Create Date: 10.05.2021 16:59:05
// Design Name: 
// Module Name: Counter
// Project Name: 
// Target Devices: 
// Tool Versions: 
// Description: 
// 
// Dependencies: 
// 
// Revision:
// Revision 0.01 - File Created
// Additional Comments:
// 
//////////////////////////////////////////////////////////////////////////////////


module Counter(
output reg [3:0]R2,input load,input increment,input clk,input reset_b);
always @(posedge clk,negedge reset_b)
   if(reset_b == 0) R2<=0;
   else if (load ==1) R2<=4'b1111;
   else if(increment==1) R2<=R2+1;
endmodule

OneDrive/Documents/VivadoCodes/count_1s/count_1s.srcs/sources_1/new/Shiftreg.v
`timescale 1ns / 1ps
//////////////////////////////////////////////////////////////////////////////////
// Company: 
// Engineer: 
// 
// Create Date: 10.05.2021 16:49:21
// Design Name: 
// Module Name: Shiftreg
// Project Name: 
// Target Devices: 
// Tool Versions: 
// Description: 
// 
// Dependencies: 
// 
// Revision:
// Revision 0.01 - File Created
// Additional Comments:
// 
//////////////////////////////////////////////////////////////////////////////////


module Shiftreg(
output reg [7:0] R1,input [7:0]data,input value_shift,input shift_l,input load,input clk,input reset_b);
always @(posedge clk,negedge reset_b)
    if(reset_b == 0) R1 <= 8'h00;
    else
      begin
       if(load ==1) R1 <= data;
       else if(shift_l ==1) R1 <= {R1[6:0],value_shift};
      end       
endmodule

OneDrive/Documents/VivadoCodes/count_1s/count_1s.srcs/sources_1/new/Datapath.v
`timescale 1ns / 1ps
//////////////////////////////////////////////////////////////////////////////////
// Company: 
// Engineer: 
// 
// Create Date: 09.05.2021 17:22:30
// Design Name: 
// Module Name: Datapath
// Project Name: 
// Target Devices: 
// Tool Versions: 
// Description: 
// 
// Dependencies: 
// 
// Revision:
// Revision 0.01 - File Created
// Additional Comments:
// 
//////////////////////////////////////////////////////////////////////////////////


module Datapath(
output [3:0]count,input load,input shift_l,input increment,input [7:0] data,input clk,output zero,output E );
wire [7:0]R1;    //contains the shifted number
wire zero;   // this is the value to be shifted into E
supply0 GND;
supply1 Vcc;
assign zero =  (R1==0);
Shiftreg DUT1(R1,data,GND,shift_l,load,clk,Vcc);
Counter DUT2(count,load,increment,clk,Vcc);
flipflopdata flipflop(E,e_in,Vcc,clk);
and G1(e_in,R1[7],shift_l);
endmodule

OneDrive/Documents/VivadoCodes/count_1s/count_1s.srcs/sources_1/new/decoder2x4.v
`timescale 1ns / 1ps
//////////////////////////////////////////////////////////////////////////////////
// Company: 
// Engineer: 
// 
// Create Date: 10.05.2021 16:28:02
// Design Name: 
// Module Name: decoder2x4
// Project Name: 
// Target Devices: 
// Tool Versions: 
// Description: 
// 
// Dependencies: 
// 
// Revision:
// Revision 0.01 - File Created
// Additional Comments:
// 
//////////////////////////////////////////////////////////////////////////////////


module decoder2x4(
output [0:3] out,input in1,input in0,input enable);
assign out[0] = !(!in1 && !in0 && !enable),
       out[1] = !(!in1 && in0  && !enable),
       out[2] = !(in1 && !in0  && !enable),
       out[3] = !(in1 && in0  && !enable);
 endmodule

OneDrive/Documents/VivadoCodes/count_1s/count_1s.srcs/sources_1/new/Dff.v
`timescale 1ns / 1ps
//////////////////////////////////////////////////////////////////////////////////
// Company: 
// Engineer: 
// 
// Create Date: 10.05.2021 16:22:27
// Design Name: 
// Module Name: Dff
// Project Name: 
// Target Devices: 
// Tool Versions: 
// Description: 
// 
// Dependencies: 
// 
// Revision:
// Revision 0.01 - File Created
// Additional Comments:
// 
//////////////////////////////////////////////////////////////////////////////////


module Dff(
output reg q,output q_b,input d,input clk,input reset_b);
assign q_b = ~q;
always@(posedge clk,negedge reset_b)
    if(reset_b == 0)
       q <= 1'b0;
    else
       q <= d;   
 endmodule

OneDrive/Documents/VivadoCodes/count_1s/count_1s.srcs/sources_1/new/mux_4x1.v
`timescale 1ns / 1ps
//////////////////////////////////////////////////////////////////////////////////
// Company: 
// Engineer: 
// 
// Create Date: 10.05.2021 16:18:12
// Design Name: 
// Module Name: mux_4x1
// Project Name: 
// Target Devices: 
// Tool Versions: 
// Description: 
// 
// Dependencies: 
// 
// Revision:
// Revision 0.01 - File Created
// Additional Comments:
// 
//////////////////////////////////////////////////////////////////////////////////


module mux_4x1(
input a1,input a2,input a3,input a4,output reg out,input [1:0]sel);
always @(a1,a2,a3,a4,sel)
    case(sel)
    2'b00: out = a1;
    2'b01: out = a2;
    2'b10: out = a3;
    2'b11: out = a4;
    endcase
endmodule

OneDrive/Documents/VivadoCodes/count_1s/count_1s.srcs/sources_1/new/Controller.v
`timescale 1ns / 1ps
//////////////////////////////////////////////////////////////////////////////////
// Company: 
// Engineer: 
// 
// Create Date: 09.05.2021 16:20:14
// Design Name: 
// Module Name: Controller
// Project Name: 
// Target Devices: 
// Tool Versions: 
// Description: 
// 
// Dependencies: 
// 
// Revision:
// Revision 0.01 - File Created
// Additional Comments:
// 
//////////////////////////////////////////////////////////////////////////////////


module Controller(output ready,input clk,input start,input reset_b,output load,output shift,output increment,input zero,input E);
wire E_b = ~E;
wire G0,G0_b,G1,G1_b,D0_in,D1_in,load,shift,increment;  //G0,G1 are the outputs of flipflops
wire zero_b = ~zero;               //to tell whether the number is zero
wire [1:0]sel = {G1,G0};
wire [0:3]dec_output;
supply0 GND;
supply1 Vcc;
parameter S_idle = 2'b00,S_1=2'b01,S_2 = 2'b10,S_3 = 2'b11;
assign ready = ~dec_output[0];
assign increment = ~dec_output[1];
assign shift  = ~dec_output[2];
and Gate1(load,ready,start);                                   
mux_4x1 MUX1(D1_in,GND,zero_b,Vcc,E_b,sel);
mux_4x1 MUX2(D0_in,start,GND,Vcc,E,sel);
Dff FF1(G1,G1_b,D1_in,clk,reset_b);
Dff FF0(G0,G0_b,D0_in,clk,reset_b);
decoder2x4 Dec(dec_output,G1,G0,GND);
endmodule

OneDrive/Documents/VivadoCodes/count_1s/count_1s.srcs/sources_1/new/counter_1.v
`timescale 1ns / 1ps
//////////////////////////////////////////////////////////////////////////////////
// Company: 
// Engineer: 
// 
// Create Date: 09.05.2021 16:04:37
// Design Name: 
// Module Name: counter_1
// Project Name: 
// Target Devices: 
// Tool Versions: 
// Description: 
// 
// Dependencies: 
// 
// Revision:
// Revision 0.01 - File Created
// Additional Comments:
// 
//////////////////////////////////////////////////////////////////////////////////


module counter_1(
input clk,input start,input [7:0] data,input reset_b,output [3:0]count,output ready);

wire load,shift_l,increment,zero,E;
Controller M1(.ready(ready),.clk(clk),.start(start),.reset_b(reset_b),.load(load),.shift(shift_l),.increment(increment),.zero(zero),.E(E));
Datapath   M2(.data(data),.count(count),.clk(clk),.load(load),.shift_l(shift_l),.increment(increment),.zero(zero),.E(E));
endmodule

OneDrive/Documents/VivadoCodes/count_1s/count_1s.srcs/sim_1/new/count1s_tb.v
`timescale 1ns / 1ps
//////////////////////////////////////////////////////////////////////////////////
// Company: 
// Engineer: 
// 
// Create Date: 10.05.2021 17:34:47
// Design Name: 
// Module Name: count1s_tb
// Project Name: 
// Target Devices: 
// Tool Versions: 
// Description: 
// 
// Dependencies: 
// 
// Revision:
// Revision 0.01 - File Created
// Additional Comments:
// 
//////////////////////////////////////////////////////////////////////////////////


module count1s_tb;
reg clk,start,reset_b;
wire [3:0]R2;
reg [7:0] data;
wire [3:0] count;
wire ready;
counter_1 DUT(clk,start,data,reset_b,count,ready);
initial #650 $finish;
initial begin
 clk=0;
  forever #5 clk = ~clk;
  end
 

initial fork
#1 reset_b=1;
#3 reset_b=0;
#4 reset_b=1;
#27 reset_b=0;
#29 reset_b=1;
#355 reset_b=0;
#365 reset_b=1;
#4 data=8'Hff;
#145 data=8'haa;
#25 start=1;
#35 start=0;
#55 start=1;
#65 start=0;
#395 start=1;
#405 start=0;
 join
endmodule

OneDrive/Documents/VivadoCodes/count_1s/count_1s.sim/sim_1/behav/xsim/count.vcd
$date
   Tue May 11 15:01:09 2021
$end
$version
  2020.2
$end
$timescale
  1ps
$end
$scope module count1s_tb $end
$var reg 1 ! clk $end
$var reg 1 " start $end
$var reg 1 # reset_b $end
$var reg 8 $ data [7:0] $end
$var wire 4 % count [3:0] $end
$var wire 1 & ready $end
$upscope $end
$enddefinitions $end
#0
$dumpvars
0!
x"
x#
bx $
bx %
x&
$end
#1000
1#
#3000
0#
0&
#4000
1#
b11111111 $
#5000
1!
x&
#10000
0!
#15000
1!
#20000
0!
#25000
1!
1"
#27000
0#
0&
#29000
1#
#30000
0!
#35000
1!
0"
x&
#40000
0!
#45000
1!
#50000
0!
#55000
1!
1"
#60000
0!
#65000
1!
0"
#70000
0!
#75000
1!
#80000
0!
#85000
1!
#90000
0!
#95000
1!
#100000
0!
#105000
1!
#110000
0!
#115000
1!
#120000
0!
#125000
1!
#130000
0!
#135000
1!
#140000
0!
#145000
1!
b10101010 $
